fast_trie/__init__.py
fast_trie/fast_trie.py
fast_trie_set-0.6.1.dist-info/LICENSE
fast_trie_set-0.6.1.dist-info/METADATA
fast_trie_set-0.6.1.dist-info/WHEEL
fast_trie_set-0.6.1.dist-info/top_level.txt
fast_trie_set-0.6.1.dist-info/RECORD
