Metadata-Version: 2.1
Name: fast-trie-set
Version: 0.6.1
Summary: A fast and efficient trie-based collection for storing and searching millions of strings.
Home-page: https://github.com/YashrajSinghRawat/fast_trie
Author: Yashraj Singh Rawat
Author-email: yashraj22august@gmail.com
License: MIT
Platform: UNKNOWN
Classifier: Programming Language :: Python :: 3
Classifier: License :: OSI Approved :: MIT License
Classifier: Operating System :: OS Independent
Requires-Python: >=3.6
